ipsuite/__init__.py
ipsuite/__init__.pyi
ipsuite/abc.py
ipsuite/version.py
ipsuite/analysis/__init__.py
ipsuite/analysis/bin_property.py
ipsuite/analysis/bond_stretch.py
ipsuite/analysis/ensemble.py
ipsuite/analysis/forces.py
ipsuite/analysis/md.py
ipsuite/analysis/molecules.py
ipsuite/analysis/sensitivity.py
ipsuite/analysis/model/__init__.py
ipsuite/analysis/model/dynamics.py
ipsuite/analysis/model/math.py
ipsuite/analysis/model/plots.py
ipsuite/analysis/model/predict.py
ipsuite/base/__init__.py
ipsuite/base/base.py
ipsuite/base/protocol.py
ipsuite/bootstrap/__init__.py
ipsuite/bootstrap/random_displacements.py
ipsuite/bootstrap/surface_mods.py
ipsuite/calc/__init__.py
ipsuite/calc/apply.py
ipsuite/calculators/__init__.py
ipsuite/calculators/__init__.pyi
ipsuite/calculators/ase_geoopt.py
ipsuite/calculators/ase_standard.py
ipsuite/calculators/cp2k.py
ipsuite/calculators/integrators.py
ipsuite/calculators/lammps.py
ipsuite/calculators/mix.py
ipsuite/calculators/orca.py
ipsuite/calculators/plumed.py
ipsuite/calculators/xtb.py
ipsuite/configuration_generation/__init__.py
ipsuite/configuration_generation/__init__.pyi
ipsuite/configuration_generation/gmx.py
ipsuite/configuration_generation/packmol.py
ipsuite/configuration_generation/smiles_to_atoms.py
ipsuite/configuration_selection/__init__.py
ipsuite/configuration_selection/base.py
ipsuite/configuration_selection/filter.py
ipsuite/configuration_selection/index.py
ipsuite/configuration_selection/random.py
ipsuite/configuration_selection/split.py
ipsuite/configuration_selection/threshold.py
ipsuite/configuration_selection/uniform_arange.py
ipsuite/configuration_selection/uniform_energetic.py
ipsuite/configuration_selection/uniform_temporal.py
ipsuite/data_loading/__init__.py
ipsuite/data_loading/add_data_ase.py
ipsuite/data_loading/add_data_h5md.py
ipsuite/datasets/__init__.py
ipsuite/datasets/md22.py
ipsuite/dynamics/__init__.py
ipsuite/dynamics/checks.py
ipsuite/dynamics/constraints.py
ipsuite/dynamics/md.py
ipsuite-0.2.7.dist-info/METADATA
ipsuite-0.2.7.dist-info/WHEEL
ipsuite-0.2.7.dist-info/licenses/LICENSE
ipsuite-0.2.7.dist-info/RECORD
