Metadata-Version: 2.4
Name: ipsuite
Version: 0.2.7
Summary: A suite of tools for machine learned interatomic potentials.
Project-URL: Repository, https://github.com/zincware/ipsuite
Project-URL: Releases, https://github.com/zincware/ipsuite/releases
Project-URL: Discord, https://discord.gg/7ncfwhsnm4
Project-URL: Documentation, https://ipsuite.readthedocs.io
Author-email: Fabian Zills <fzills@icp.uni-stuttgart.de>, Moritz René Schäfer <schaefer@theochem.uni-stuttgart.de>, Nico Segreto <segreto@theochem.uni-stuttgart.de>
License-File: LICENSE
Keywords: data-version-control,interatomic potentials,machine-learning,reproducibility
Classifier: License :: OSI Approved :: Eclipse Public License 2.0 (EPL-2.0)
Requires-Python: >=3.10
Requires-Dist: ase>=3.24.0
Requires-Dist: laufband>=0.1.5
Requires-Dist: lazy-loader>=0.4
Requires-Dist: pint>=0.24.4
Requires-Dist: rdkit2ase>=0.1.7
Requires-Dist: seaborn>=0.13.2
Requires-Dist: uncertainty-toolbox>=0.1.1
Requires-Dist: znh5md>=0.4.7
Requires-Dist: zntrack>=0.8.7
